{"metadata":{},"options":{"compact":false,"sourceMaps":true,"ast":true,"babelrc":false,"configFile":false,"parserOpts":{"sourceType":"module","sourceFileName":"/Users/tilenbabnik/Desktop/pgg/packages/empirica:core/ui/components/admin/AdminHeading.jsx","plugins":["*","flow","jsx","asyncGenerators","bigInt","classPrivateMethods","classPrivateProperties","classProperties","doExpressions","dynamicImport","exportDefaultFrom","exportExtensions","exportNamespaceFrom","functionBind","functionSent","importMeta","nullishCoalescingOperator","numericSeparator","objectRestSpread","optionalCatchBinding","optionalChaining",["pipelineOperator",{"proposal":"minimal"}],"throwExpressions","classProperties","classPrivateProperties","jsx","nullishCoalescingOperator","nullishCoalescingOperator","optionalChaining","optionalChaining","optionalCatchBinding","optionalCatchBinding","classProperties","classPrivateProperties","classPrivateMethods","classProperties","classPrivateProperties","asyncGenerators","asyncGenerators","objectRestSpread","objectRestSpread"],"allowImportExportEverywhere":true,"allowReturnOutsideFunction":true,"allowUndeclaredExports":true,"strictMode":false},"caller":{"name":"meteor","arch":"web.browser"},"sourceFileName":"packages/empirica:core/ui/components/admin/AdminHeading.jsx","filename":"/Users/tilenbabnik/Desktop/pgg/packages/empirica:core/ui/components/admin/AdminHeading.jsx","passPerPreset":false,"envName":"development","cwd":"/Users/tilenbabnik/Desktop/pgg","root":"/Users/tilenbabnik/Desktop/pgg","plugins":[{"key":"base$0","visitor":{"_exploded":true,"_verified":true},"options":{}},{"key":"base$0$0","visitor":{"Program":{"enter":[null],"exit":[null]},"_exploded":true,"_verified":true},"options":{"avoidModernSyntax":false,"enforceStrictMode":false,"dynamicImport":true,"generateLetDeclarations":true}},{"key":"transform-runtime","visitor":{"CallExpression":{"enter":[null]},"BinaryExpression":{"enter":[null]},"MemberExpression":{"enter":[null],"exit":[null]},"_exploded":true,"_verified":true,"Identifier":{"enter":[null]},"JSXIdentifier":{"enter":[null]}},"options":{"version":"7.9.2","helpers":true,"useESModules":false,"corejs":false}},{"key":"proposal-class-properties","visitor":{"PrivateName":{"enter":[null]},"ExportDefaultDeclaration":{"enter":[null]},"_exploded":true,"_verified":true,"ClassExpression":{"enter":[null]},"ClassDeclaration":{"enter":[null]}},"options":{"loose":true}},{"key":"transform-react-jsx","visitor":{"_exploded":{},"_verified":{},"JSXNamespacedName":{"enter":[null]},"JSXSpreadChild":{"enter":[null]},"JSXElement":{"exit":[null]},"JSXFragment":{"exit":[null]},"Program":{"enter":[null],"exit":[null]},"JSXAttribute":{"enter":[null]}},"options":{"pragma":"React.createElement","pragmaFrag":"React.Fragment","runtime":"classic","throwIfNamespace":true,"useBuiltIns":false}},{"key":"transform-react-display-name","visitor":{"ExportDefaultDeclaration":{"enter":[null]},"CallExpression":{"enter":[null]},"_exploded":true,"_verified":true},"options":{}},{"key":"syntax-nullish-coalescing-operator","visitor":{"_exploded":true,"_verified":true},"options":{}},{"key":"proposal-nullish-coalescing-operator","visitor":{"_exploded":{},"_verified":{},"LogicalExpression":{"enter":[null]}},"options":{}},{"key":"syntax-optional-chaining","visitor":{"_exploded":true,"_verified":true},"options":{}},{"key":"proposal-optional-chaining","visitor":{"_exploded":{},"_verified":{},"OptionalCallExpression":{"enter":[null]},"OptionalMemberExpression":{"enter":[null]}},"options":{}},{"key":"syntax-optional-catch-binding","visitor":{"_exploded":true,"_verified":true},"options":{}},{"key":"proposal-optional-catch-binding","visitor":{"_exploded":{},"_verified":{},"CatchClause":{"enter":[null]}},"options":{}},{"key":"syntax-class-properties","visitor":{"_exploded":true,"_verified":true},"options":{}},{"key":"proposal-class-properties","visitor":{"PrivateName":{"enter":[null]},"ExportDefaultDeclaration":{"enter":[null]},"_exploded":true,"_verified":true,"ClassExpression":{"enter":[null]},"ClassDeclaration":{"enter":[null]}},"options":{}},{"key":"syntax-async-generators","visitor":{"_exploded":true,"_verified":true},"options":{}},{"key":"proposal-async-generator-functions","visitor":{"_exploded":{},"_verified":{},"Program":{"enter":[null]}},"options":{}},{"key":"syntax-object-rest-spread","visitor":{"_exploded":true,"_verified":true},"options":{}},{"key":"proposal-object-rest-spread","visitor":{"_exploded":{},"_verified":{},"VariableDeclarator":{"enter":[null]},"ExportNamedDeclaration":{"enter":[null]},"CatchClause":{"enter":[null]},"AssignmentExpression":{"enter":[null]},"ArrayPattern":{"enter":[null]},"ObjectExpression":{"enter":[null]},"FunctionDeclaration":{"enter":[null]},"FunctionExpression":{"enter":[null]},"ObjectMethod":{"enter":[null]},"ArrowFunctionExpression":{"enter":[null]},"ClassMethod":{"enter":[null]},"ClassPrivateMethod":{"enter":[null]},"ForInStatement":{"enter":[null]},"ForOfStatement":{"enter":[null]}},"options":{}},{"key":"transform-literals","visitor":{"NumericLiteral":{"enter":[null]},"StringLiteral":{"enter":[null]},"_exploded":true,"_verified":true},"options":{}},{"key":"transform-template-literals","visitor":{"TaggedTemplateExpression":{"enter":[null]},"TemplateLiteral":{"enter":[null]},"_exploded":true,"_verified":true},"options":{}},{"key":"transform-parameters","visitor":{"_exploded":true,"_verified":true,"FunctionDeclaration":{"enter":[null]},"FunctionExpression":{"enter":[null]},"ObjectMethod":{"enter":[null]},"ArrowFunctionExpression":{"enter":[null]},"ClassMethod":{"enter":[null]},"ClassPrivateMethod":{"enter":[null]}},"options":{}},{"key":"transform-exponentiation-operator","visitor":{"AssignmentExpression":{"enter":[null]},"BinaryExpression":{"enter":[null]},"_exploded":true,"_verified":true},"options":{}}],"presets":[],"generatorOpts":{"filename":"/Users/tilenbabnik/Desktop/pgg/packages/empirica:core/ui/components/admin/AdminHeading.jsx","comments":true,"compact":false,"sourceMaps":true,"sourceFileName":"packages/empirica:core/ui/components/admin/AdminHeading.jsx"}},"code":"let _extends;\n\nmodule.link(\"@babel/runtime/helpers/extends\", {\n  default(v) {\n    _extends = v;\n  }\n\n}, 0);\nmodule.export({\n  AdminPageHeader: () => AdminPageHeader\n});\nlet React;\nmodule.link(\"react\", {\n  default(v) {\n    React = v;\n  }\n\n}, 0);\nlet Icon;\nmodule.link(\"@blueprintjs/core\", {\n  Icon(v) {\n    Icon = v;\n  }\n\n}, 1);\nlet H2;\nmodule.link(\"../Heading.jsx\", {\n  H2(v) {\n    H2 = v;\n  }\n\n}, 2);\n\nconst AdminPageHeader = props => /*#__PURE__*/React.createElement(H2, _extends({\n  className: \"admin-heading\",\n  iconSize: Icon.SIZE_LARGE\n}, props));","map":{"version":3,"sources":["packages/empirica:core/ui/components/admin/AdminHeading.jsx"],"names":["_extends","module","link","default","v","export","AdminPageHeader","React","Icon","H2","props","SIZE_LARGE"],"mappings":"AAAA,IAAIA,QAAJ;;AAAaC,MAAM,CAACC,IAAP,CAAY,gCAAZ,EAA6C;AAACC,EAAAA,OAAO,CAACC,CAAD,EAAG;AAACJ,IAAAA,QAAQ,GAACI,CAAT;AAAW;;AAAvB,CAA7C,EAAsE,CAAtE;AAAbH,MAAM,CAACI,MAAP,CAAc;AAACC,EAAAA,eAAe,EAAC,MAAIA;AAArB,CAAd;AAAqD,IAAIC,KAAJ;AAAUN,MAAM,CAACC,IAAP,CAAY,OAAZ,EAAoB;AAACC,EAAAA,OAAO,CAACC,CAAD,EAAG;AAACG,IAAAA,KAAK,GAACH,CAAN;AAAQ;;AAApB,CAApB,EAA0C,CAA1C;AAA6C,IAAII,IAAJ;AAASP,MAAM,CAACC,IAAP,CAAY,mBAAZ,EAAgC;AAACM,EAAAA,IAAI,CAACJ,CAAD,EAAG;AAACI,IAAAA,IAAI,GAACJ,CAAL;AAAO;;AAAhB,CAAhC,EAAkD,CAAlD;AAAqD,IAAIK,EAAJ;AAAOR,MAAM,CAACC,IAAP,CAAY,gBAAZ,EAA6B;AAACO,EAAAA,EAAE,CAACL,CAAD,EAAG;AAACK,IAAAA,EAAE,GAACL,CAAH;AAAK;;AAAZ,CAA7B,EAA2C,CAA3C;;AAO1K,MAAME,eAAe,GAAGI,KAAK,iBAClC,oBAAC,EAAD;AAAI,EAAA,SAAS,EAAC,eAAd;AAA8B,EAAA,QAAQ,EAAEF,IAAI,CAACG;AAA7C,GAA6DD,KAA7D,EADK","sourcesContent":["// This is only to be able to centralize the style of admin headings.\nimport React from \"react\";\n\nimport { Icon } from \"@blueprintjs/core\";\n\nimport { H2 } from \"../Heading.jsx\";\n\nexport const AdminPageHeader = props => (\n  <H2 className=\"admin-heading\" iconSize={Icon.SIZE_LARGE} {...props} />\n);\n"]},"sourceType":"module","hash":"2f2376ffa9d8d3b385d3cd3e2271f63fdd8e2b31"}
