{"metadata":{},"options":{"compact":false,"sourceMaps":true,"ast":true,"babelrc":false,"configFile":false,"parserOpts":{"sourceType":"module","sourceFileName":"/Users/tilenbabnik/Desktop/pgg/packages/empirica:core/api/player-stages/methods.js","plugins":["*","flow","jsx","asyncGenerators","bigInt","classPrivateMethods","classPrivateProperties","classProperties","doExpressions","dynamicImport","exportDefaultFrom","exportExtensions","exportNamespaceFrom","functionBind","functionSent","importMeta","nullishCoalescingOperator","numericSeparator","objectRestSpread","optionalCatchBinding","optionalChaining",["pipelineOperator",{"proposal":"minimal"}],"throwExpressions","classProperties","classPrivateProperties","jsx","nullishCoalescingOperator","nullishCoalescingOperator","optionalChaining","optionalChaining","optionalCatchBinding","optionalCatchBinding","classProperties","classPrivateProperties","classPrivateMethods","classProperties","classPrivateProperties","asyncGenerators","asyncGenerators","objectRestSpread","objectRestSpread"],"allowImportExportEverywhere":true,"allowReturnOutsideFunction":true,"allowUndeclaredExports":true,"strictMode":false},"caller":{"name":"meteor","arch":"web.browser"},"sourceFileName":"packages/empirica:core/api/player-stages/methods.js","filename":"/Users/tilenbabnik/Desktop/pgg/packages/empirica:core/api/player-stages/methods.js","passPerPreset":false,"envName":"development","cwd":"/Users/tilenbabnik/Desktop/pgg","root":"/Users/tilenbabnik/Desktop/pgg","plugins":[{"key":"base$0","visitor":{"_exploded":true,"_verified":true},"options":{}},{"key":"base$0$0","visitor":{"Program":{"enter":[null],"exit":[null]},"_exploded":true,"_verified":true},"options":{"avoidModernSyntax":false,"enforceStrictMode":false,"dynamicImport":true,"generateLetDeclarations":true}},{"key":"transform-runtime","visitor":{"CallExpression":{"enter":[null]},"BinaryExpression":{"enter":[null]},"MemberExpression":{"enter":[null],"exit":[null]},"_exploded":true,"_verified":true,"Identifier":{"enter":[null]},"JSXIdentifier":{"enter":[null]}},"options":{"version":"7.9.2","helpers":true,"useESModules":false,"corejs":false}},{"key":"proposal-class-properties","visitor":{"PrivateName":{"enter":[null]},"ExportDefaultDeclaration":{"enter":[null]},"_exploded":true,"_verified":true,"ClassExpression":{"enter":[null]},"ClassDeclaration":{"enter":[null]}},"options":{"loose":true}},{"key":"transform-react-jsx","visitor":{"_exploded":{},"_verified":{},"JSXNamespacedName":{"enter":[null]},"JSXSpreadChild":{"enter":[null]},"JSXElement":{"exit":[null]},"JSXFragment":{"exit":[null]},"Program":{"enter":[null],"exit":[null]},"JSXAttribute":{"enter":[null]}},"options":{"pragma":"React.createElement","pragmaFrag":"React.Fragment","runtime":"classic","throwIfNamespace":true,"useBuiltIns":false}},{"key":"transform-react-display-name","visitor":{"ExportDefaultDeclaration":{"enter":[null]},"CallExpression":{"enter":[null]},"_exploded":true,"_verified":true},"options":{}},{"key":"syntax-nullish-coalescing-operator","visitor":{"_exploded":true,"_verified":true},"options":{}},{"key":"proposal-nullish-coalescing-operator","visitor":{"_exploded":{},"_verified":{},"LogicalExpression":{"enter":[null]}},"options":{}},{"key":"syntax-optional-chaining","visitor":{"_exploded":true,"_verified":true},"options":{}},{"key":"proposal-optional-chaining","visitor":{"_exploded":{},"_verified":{},"OptionalCallExpression":{"enter":[null]},"OptionalMemberExpression":{"enter":[null]}},"options":{}},{"key":"syntax-optional-catch-binding","visitor":{"_exploded":true,"_verified":true},"options":{}},{"key":"proposal-optional-catch-binding","visitor":{"_exploded":{},"_verified":{},"CatchClause":{"enter":[null]}},"options":{}},{"key":"syntax-class-properties","visitor":{"_exploded":true,"_verified":true},"options":{}},{"key":"proposal-class-properties","visitor":{"PrivateName":{"enter":[null]},"ExportDefaultDeclaration":{"enter":[null]},"_exploded":true,"_verified":true,"ClassExpression":{"enter":[null]},"ClassDeclaration":{"enter":[null]}},"options":{}},{"key":"syntax-async-generators","visitor":{"_exploded":true,"_verified":true},"options":{}},{"key":"proposal-async-generator-functions","visitor":{"_exploded":{},"_verified":{},"Program":{"enter":[null]}},"options":{}},{"key":"syntax-object-rest-spread","visitor":{"_exploded":true,"_verified":true},"options":{}},{"key":"proposal-object-rest-spread","visitor":{"_exploded":{},"_verified":{},"VariableDeclarator":{"enter":[null]},"ExportNamedDeclaration":{"enter":[null]},"CatchClause":{"enter":[null]},"AssignmentExpression":{"enter":[null]},"ArrayPattern":{"enter":[null]},"ObjectExpression":{"enter":[null]},"FunctionDeclaration":{"enter":[null]},"FunctionExpression":{"enter":[null]},"ObjectMethod":{"enter":[null]},"ArrowFunctionExpression":{"enter":[null]},"ClassMethod":{"enter":[null]},"ClassPrivateMethod":{"enter":[null]},"ForInStatement":{"enter":[null]},"ForOfStatement":{"enter":[null]}},"options":{}},{"key":"transform-literals","visitor":{"NumericLiteral":{"enter":[null]},"StringLiteral":{"enter":[null]},"_exploded":true,"_verified":true},"options":{}},{"key":"transform-template-literals","visitor":{"TaggedTemplateExpression":{"enter":[null]},"TemplateLiteral":{"enter":[null]},"_exploded":true,"_verified":true},"options":{}},{"key":"transform-parameters","visitor":{"_exploded":true,"_verified":true,"FunctionDeclaration":{"enter":[null]},"FunctionExpression":{"enter":[null]},"ObjectMethod":{"enter":[null]},"ArrowFunctionExpression":{"enter":[null]},"ClassMethod":{"enter":[null]},"ClassPrivateMethod":{"enter":[null]}},"options":{}},{"key":"transform-exponentiation-operator","visitor":{"AssignmentExpression":{"enter":[null]},"BinaryExpression":{"enter":[null]},"_exploded":true,"_verified":true},"options":{}}],"presets":[],"generatorOpts":{"filename":"/Users/tilenbabnik/Desktop/pgg/packages/empirica:core/api/player-stages/methods.js","comments":true,"compact":false,"sourceMaps":true,"sourceFileName":"packages/empirica:core/api/player-stages/methods.js"}},"code":"module.export({\n  updatePlayerStageData: () => updatePlayerStageData,\n  submitPlayerStage: () => submitPlayerStage\n});\nlet ValidatedMethod;\nmodule.link(\"meteor/mdg:validated-method\", {\n  ValidatedMethod(v) {\n    ValidatedMethod = v;\n  }\n\n}, 0);\nlet SimpleSchema;\nmodule.link(\"simpl-schema\", {\n  default(v) {\n    SimpleSchema = v;\n  }\n\n}, 1);\nlet PlayerStages;\nmodule.link(\"./player-stages\", {\n  PlayerStages(v) {\n    PlayerStages = v;\n  }\n\n}, 2);\nlet shared;\nmodule.link(\"../../shared.js\", {\n  default(v) {\n    shared = v;\n  }\n\n}, 3);\nconst updatePlayerStageData = new ValidatedMethod({\n  name: \"PlayerStages.methods.updateData\",\n  validate: new SimpleSchema({\n    playerStageId: {\n      type: String,\n      regEx: SimpleSchema.RegEx.Id\n    },\n    key: {\n      type: String\n    },\n    value: {\n      type: String\n    },\n    append: {\n      type: Boolean,\n      optional: true\n    },\n    noCallback: {\n      type: Boolean,\n      optional: true\n    }\n  }).validator(),\n\n  run(_ref) {\n    let {\n      playerStageId,\n      key,\n      value,\n      append,\n      noCallback\n    } = _ref;\n    const playerStage = PlayerStages.findOne(playerStageId);\n\n    if (!playerStage) {\n      throw new Error(\"playerStage not found\");\n    } // TODO check can update this record playerStage\n\n\n    const val = JSON.parse(value);\n    let update = {\n      [\"data.\".concat(key)]: val\n    };\n    const modifier = append ? {\n      $push: update\n    } : {\n      $set: update\n    };\n    PlayerStages.update(playerStageId, modifier, {\n      autoConvert: false,\n      filter: false,\n      validate: false,\n      trimStrings: false,\n      removeEmptyStrings: false\n    });\n\n    if (Meteor.isServer && !noCallback) {\n      shared.callOnChange({\n        playerId: playerStage.playerId,\n        playerStageId,\n        playerStage,\n        key,\n        value: val,\n        prevValue: playerStage.data && playerStage.data[key],\n        append\n      });\n    }\n  }\n\n});\nconst submitPlayerStage = new ValidatedMethod({\n  name: \"PlayerStages.methods.submit\",\n  validate: new SimpleSchema({\n    playerStageId: {\n      type: String,\n      regEx: SimpleSchema.RegEx.Id\n    },\n    noCallback: {\n      type: Boolean,\n      optional: true\n    }\n  }).validator(),\n\n  run(_ref2) {\n    let {\n      playerStageId,\n      noCallback\n    } = _ref2;\n    const playerStage = PlayerStages.findOne(playerStageId);\n\n    if (!playerStage) {\n      throw new Error(\"playerStage not found\");\n    } // TODO check can update this record playerStage\n\n\n    if (playerStage.submittedAt) {\n      if (Meteor.isDevelopment) {\n        console.log(\"stage already submitted\");\n      }\n\n      return;\n    }\n\n    PlayerStages.update(playerStageId, {\n      $set: {\n        submittedAt: new Date()\n      }\n    });\n\n    if (Meteor.isServer && !noCallback) {\n      shared.callOnSubmit({\n        playerId: playerStage.playerId,\n        playerStage\n      });\n    }\n  }\n\n});","map":{"version":3,"sources":["packages/empirica:core/api/player-stages/methods.js"],"names":["module","export","updatePlayerStageData","submitPlayerStage","ValidatedMethod","link","v","SimpleSchema","default","PlayerStages","shared","name","validate","playerStageId","type","String","regEx","RegEx","Id","key","value","append","Boolean","optional","noCallback","validator","run","playerStage","findOne","Error","val","JSON","parse","update","modifier","$push","$set","autoConvert","filter","trimStrings","removeEmptyStrings","Meteor","isServer","callOnChange","playerId","prevValue","data","submittedAt","isDevelopment","console","log","Date","callOnSubmit"],"mappings":"AAAAA,MAAM,CAACC,MAAP,CAAc;AAACC,EAAAA,qBAAqB,EAAC,MAAIA,qBAA3B;AAAiDC,EAAAA,iBAAiB,EAAC,MAAIA;AAAvE,CAAd;AAAyG,IAAIC,eAAJ;AAAoBJ,MAAM,CAACK,IAAP,CAAY,6BAAZ,EAA0C;AAACD,EAAAA,eAAe,CAACE,CAAD,EAAG;AAACF,IAAAA,eAAe,GAACE,CAAhB;AAAkB;;AAAtC,CAA1C,EAAkF,CAAlF;AAAqF,IAAIC,YAAJ;AAAiBP,MAAM,CAACK,IAAP,CAAY,cAAZ,EAA2B;AAACG,EAAAA,OAAO,CAACF,CAAD,EAAG;AAACC,IAAAA,YAAY,GAACD,CAAb;AAAe;;AAA3B,CAA3B,EAAwD,CAAxD;AAA2D,IAAIG,YAAJ;AAAiBT,MAAM,CAACK,IAAP,CAAY,iBAAZ,EAA8B;AAACI,EAAAA,YAAY,CAACH,CAAD,EAAG;AAACG,IAAAA,YAAY,GAACH,CAAb;AAAe;;AAAhC,CAA9B,EAAgE,CAAhE;AAAmE,IAAII,MAAJ;AAAWV,MAAM,CAACK,IAAP,CAAY,iBAAZ,EAA8B;AAACG,EAAAA,OAAO,CAACF,CAAD,EAAG;AAACI,IAAAA,MAAM,GAACJ,CAAP;AAAS;;AAArB,CAA9B,EAAqD,CAArD;AAKtX,MAAMJ,qBAAqB,GAAG,IAAIE,eAAJ,CAAoB;AACvDO,EAAAA,IAAI,EAAE,iCADiD;AAGvDC,EAAAA,QAAQ,EAAE,IAAIL,YAAJ,CAAiB;AACzBM,IAAAA,aAAa,EAAE;AACbC,MAAAA,IAAI,EAAEC,MADO;AAEbC,MAAAA,KAAK,EAAET,YAAY,CAACU,KAAb,CAAmBC;AAFb,KADU;AAKzBC,IAAAA,GAAG,EAAE;AACHL,MAAAA,IAAI,EAAEC;AADH,KALoB;AAQzBK,IAAAA,KAAK,EAAE;AACLN,MAAAA,IAAI,EAAEC;AADD,KARkB;AAWzBM,IAAAA,MAAM,EAAE;AACNP,MAAAA,IAAI,EAAEQ,OADA;AAENC,MAAAA,QAAQ,EAAE;AAFJ,KAXiB;AAezBC,IAAAA,UAAU,EAAE;AACVV,MAAAA,IAAI,EAAEQ,OADI;AAEVC,MAAAA,QAAQ,EAAE;AAFA;AAfa,GAAjB,EAmBPE,SAnBO,EAH6C;;AAwBvDC,EAAAA,GAAG,OAAoD;AAAA,QAAnD;AAAEb,MAAAA,aAAF;AAAiBM,MAAAA,GAAjB;AAAsBC,MAAAA,KAAtB;AAA6BC,MAAAA,MAA7B;AAAqCG,MAAAA;AAArC,KAAmD;AACrD,UAAMG,WAAW,GAAGlB,YAAY,CAACmB,OAAb,CAAqBf,aAArB,CAApB;;AACA,QAAI,CAACc,WAAL,EAAkB;AAChB,YAAM,IAAIE,KAAJ,CAAU,uBAAV,CAAN;AACD,KAJoD,CAMrD;;;AAEA,UAAMC,GAAG,GAAGC,IAAI,CAACC,KAAL,CAAWZ,KAAX,CAAZ;AACA,QAAIa,MAAM,GAAG;AAAE,sBAASd,GAAT,IAAiBW;AAAnB,KAAb;AACA,UAAMI,QAAQ,GAAGb,MAAM,GAAG;AAAEc,MAAAA,KAAK,EAAEF;AAAT,KAAH,GAAuB;AAAEG,MAAAA,IAAI,EAAEH;AAAR,KAA9C;AAEAxB,IAAAA,YAAY,CAACwB,MAAb,CAAoBpB,aAApB,EAAmCqB,QAAnC,EAA6C;AAC3CG,MAAAA,WAAW,EAAE,KAD8B;AAE3CC,MAAAA,MAAM,EAAE,KAFmC;AAG3C1B,MAAAA,QAAQ,EAAE,KAHiC;AAI3C2B,MAAAA,WAAW,EAAE,KAJ8B;AAK3CC,MAAAA,kBAAkB,EAAE;AALuB,KAA7C;;AAQA,QAAIC,MAAM,CAACC,QAAP,IAAmB,CAAClB,UAAxB,EAAoC;AAClCd,MAAAA,MAAM,CAACiC,YAAP,CAAoB;AAClBC,QAAAA,QAAQ,EAAEjB,WAAW,CAACiB,QADJ;AAElB/B,QAAAA,aAFkB;AAGlBc,QAAAA,WAHkB;AAIlBR,QAAAA,GAJkB;AAKlBC,QAAAA,KAAK,EAAEU,GALW;AAMlBe,QAAAA,SAAS,EAAElB,WAAW,CAACmB,IAAZ,IAAoBnB,WAAW,CAACmB,IAAZ,CAAiB3B,GAAjB,CANb;AAOlBE,QAAAA;AAPkB,OAApB;AASD;AACF;;AAvDsD,CAApB,CAA9B;AA0DA,MAAMlB,iBAAiB,GAAG,IAAIC,eAAJ,CAAoB;AACnDO,EAAAA,IAAI,EAAE,6BAD6C;AAGnDC,EAAAA,QAAQ,EAAE,IAAIL,YAAJ,CAAiB;AACzBM,IAAAA,aAAa,EAAE;AACbC,MAAAA,IAAI,EAAEC,MADO;AAEbC,MAAAA,KAAK,EAAET,YAAY,CAACU,KAAb,CAAmBC;AAFb,KADU;AAKzBM,IAAAA,UAAU,EAAE;AACVV,MAAAA,IAAI,EAAEQ,OADI;AAEVC,MAAAA,QAAQ,EAAE;AAFA;AALa,GAAjB,EASPE,SATO,EAHyC;;AAcnDC,EAAAA,GAAG,QAAgC;AAAA,QAA/B;AAAEb,MAAAA,aAAF;AAAiBW,MAAAA;AAAjB,KAA+B;AACjC,UAAMG,WAAW,GAAGlB,YAAY,CAACmB,OAAb,CAAqBf,aAArB,CAApB;;AACA,QAAI,CAACc,WAAL,EAAkB;AAChB,YAAM,IAAIE,KAAJ,CAAU,uBAAV,CAAN;AACD,KAJgC,CAKjC;;;AAEA,QAAIF,WAAW,CAACoB,WAAhB,EAA6B;AAC3B,UAAIN,MAAM,CAACO,aAAX,EAA0B;AACxBC,QAAAA,OAAO,CAACC,GAAR,CAAY,yBAAZ;AACD;;AAED;AACD;;AAEDzC,IAAAA,YAAY,CAACwB,MAAb,CAAoBpB,aAApB,EAAmC;AAAEuB,MAAAA,IAAI,EAAE;AAAEW,QAAAA,WAAW,EAAE,IAAII,IAAJ;AAAf;AAAR,KAAnC;;AAEA,QAAIV,MAAM,CAACC,QAAP,IAAmB,CAAClB,UAAxB,EAAoC;AAClCd,MAAAA,MAAM,CAAC0C,YAAP,CAAoB;AAClBR,QAAAA,QAAQ,EAAEjB,WAAW,CAACiB,QADJ;AAElBjB,QAAAA;AAFkB,OAApB;AAID;AACF;;AArCkD,CAApB,CAA1B","sourcesContent":["import { ValidatedMethod } from \"meteor/mdg:validated-method\";\nimport SimpleSchema from \"simpl-schema\";\nimport { PlayerStages } from \"./player-stages\";\nimport shared from \"../../shared.js\";\n\nexport const updatePlayerStageData = new ValidatedMethod({\n  name: \"PlayerStages.methods.updateData\",\n\n  validate: new SimpleSchema({\n    playerStageId: {\n      type: String,\n      regEx: SimpleSchema.RegEx.Id\n    },\n    key: {\n      type: String\n    },\n    value: {\n      type: String\n    },\n    append: {\n      type: Boolean,\n      optional: true\n    },\n    noCallback: {\n      type: Boolean,\n      optional: true\n    }\n  }).validator(),\n\n  run({ playerStageId, key, value, append, noCallback }) {\n    const playerStage = PlayerStages.findOne(playerStageId);\n    if (!playerStage) {\n      throw new Error(\"playerStage not found\");\n    }\n\n    // TODO check can update this record playerStage\n\n    const val = JSON.parse(value);\n    let update = { [`data.${key}`]: val };\n    const modifier = append ? { $push: update } : { $set: update };\n\n    PlayerStages.update(playerStageId, modifier, {\n      autoConvert: false,\n      filter: false,\n      validate: false,\n      trimStrings: false,\n      removeEmptyStrings: false\n    });\n\n    if (Meteor.isServer && !noCallback) {\n      shared.callOnChange({\n        playerId: playerStage.playerId,\n        playerStageId,\n        playerStage,\n        key,\n        value: val,\n        prevValue: playerStage.data && playerStage.data[key],\n        append\n      });\n    }\n  }\n});\n\nexport const submitPlayerStage = new ValidatedMethod({\n  name: \"PlayerStages.methods.submit\",\n\n  validate: new SimpleSchema({\n    playerStageId: {\n      type: String,\n      regEx: SimpleSchema.RegEx.Id\n    },\n    noCallback: {\n      type: Boolean,\n      optional: true\n    }\n  }).validator(),\n\n  run({ playerStageId, noCallback }) {\n    const playerStage = PlayerStages.findOne(playerStageId);\n    if (!playerStage) {\n      throw new Error(\"playerStage not found\");\n    }\n    // TODO check can update this record playerStage\n\n    if (playerStage.submittedAt) {\n      if (Meteor.isDevelopment) {\n        console.log(\"stage already submitted\");\n      }\n\n      return;\n    }\n\n    PlayerStages.update(playerStageId, { $set: { submittedAt: new Date() } });\n\n    if (Meteor.isServer && !noCallback) {\n      shared.callOnSubmit({\n        playerId: playerStage.playerId,\n        playerStage\n      });\n    }\n  }\n});\n"]},"sourceType":"module","hash":"93ac56a28463084c0aba8da18606984d6beee8a7"}
