{"metadata":{},"options":{"compact":false,"sourceMaps":true,"ast":true,"babelrc":false,"configFile":false,"parserOpts":{"sourceType":"module","sourceFileName":"/Users/tilenbabnik/Desktop/pgg/client/game/OutcomeStage.jsx","plugins":["*","flow","jsx","asyncGenerators","bigInt","classPrivateMethods","classPrivateProperties","classProperties","doExpressions","dynamicImport","exportDefaultFrom","exportExtensions","exportNamespaceFrom","functionBind","functionSent","importMeta","nullishCoalescingOperator","numericSeparator","objectRestSpread","optionalCatchBinding","optionalChaining",["pipelineOperator",{"proposal":"minimal"}],"throwExpressions","classProperties","classPrivateProperties","jsx","nullishCoalescingOperator","nullishCoalescingOperator","optionalChaining","optionalChaining","optionalCatchBinding","optionalCatchBinding","classProperties","classPrivateProperties","classPrivateMethods","classProperties","classPrivateProperties","asyncGenerators","asyncGenerators","objectRestSpread","objectRestSpread"],"allowImportExportEverywhere":true,"allowReturnOutsideFunction":true,"allowUndeclaredExports":true,"strictMode":false},"caller":{"name":"meteor","arch":"web.browser"},"sourceFileName":"client/game/OutcomeStage.jsx","filename":"/Users/tilenbabnik/Desktop/pgg/client/game/OutcomeStage.jsx","passPerPreset":false,"envName":"development","cwd":"/Users/tilenbabnik/Desktop/pgg","root":"/Users/tilenbabnik/Desktop/pgg","plugins":[{"key":"base$0","visitor":{"_exploded":true,"_verified":true},"options":{}},{"key":"base$0$0","visitor":{"Program":{"enter":[null],"exit":[null]},"_exploded":true,"_verified":true},"options":{"avoidModernSyntax":false,"enforceStrictMode":false,"dynamicImport":true,"generateLetDeclarations":true}},{"key":"transform-runtime","visitor":{"CallExpression":{"enter":[null]},"BinaryExpression":{"enter":[null]},"MemberExpression":{"enter":[null],"exit":[null]},"_exploded":true,"_verified":true,"Identifier":{"enter":[null]},"JSXIdentifier":{"enter":[null]}},"options":{"version":"7.9.2","helpers":true,"useESModules":false,"corejs":false}},{"key":"proposal-class-properties","visitor":{"PrivateName":{"enter":[null]},"ExportDefaultDeclaration":{"enter":[null]},"_exploded":true,"_verified":true,"ClassExpression":{"enter":[null]},"ClassDeclaration":{"enter":[null]}},"options":{"loose":true}},{"key":"transform-react-jsx","visitor":{"_exploded":{},"_verified":{},"JSXNamespacedName":{"enter":[null]},"JSXSpreadChild":{"enter":[null]},"JSXElement":{"exit":[null]},"JSXFragment":{"exit":[null]},"Program":{"enter":[null],"exit":[null]},"JSXAttribute":{"enter":[null]}},"options":{"pragma":"React.createElement","pragmaFrag":"React.Fragment","runtime":"classic","throwIfNamespace":true,"useBuiltIns":false}},{"key":"transform-react-display-name","visitor":{"ExportDefaultDeclaration":{"enter":[null]},"CallExpression":{"enter":[null]},"_exploded":true,"_verified":true},"options":{}},{"key":"syntax-nullish-coalescing-operator","visitor":{"_exploded":true,"_verified":true},"options":{}},{"key":"proposal-nullish-coalescing-operator","visitor":{"_exploded":{},"_verified":{},"LogicalExpression":{"enter":[null]}},"options":{}},{"key":"syntax-optional-chaining","visitor":{"_exploded":true,"_verified":true},"options":{}},{"key":"proposal-optional-chaining","visitor":{"_exploded":{},"_verified":{},"OptionalCallExpression":{"enter":[null]},"OptionalMemberExpression":{"enter":[null]}},"options":{}},{"key":"syntax-optional-catch-binding","visitor":{"_exploded":true,"_verified":true},"options":{}},{"key":"proposal-optional-catch-binding","visitor":{"_exploded":{},"_verified":{},"CatchClause":{"enter":[null]}},"options":{}},{"key":"syntax-class-properties","visitor":{"_exploded":true,"_verified":true},"options":{}},{"key":"proposal-class-properties","visitor":{"PrivateName":{"enter":[null]},"ExportDefaultDeclaration":{"enter":[null]},"_exploded":true,"_verified":true,"ClassExpression":{"enter":[null]},"ClassDeclaration":{"enter":[null]}},"options":{}},{"key":"syntax-async-generators","visitor":{"_exploded":true,"_verified":true},"options":{}},{"key":"proposal-async-generator-functions","visitor":{"_exploded":{},"_verified":{},"Program":{"enter":[null]}},"options":{}},{"key":"syntax-object-rest-spread","visitor":{"_exploded":true,"_verified":true},"options":{}},{"key":"proposal-object-rest-spread","visitor":{"_exploded":{},"_verified":{},"VariableDeclarator":{"enter":[null]},"ExportNamedDeclaration":{"enter":[null]},"CatchClause":{"enter":[null]},"AssignmentExpression":{"enter":[null]},"ArrayPattern":{"enter":[null]},"ObjectExpression":{"enter":[null]},"FunctionDeclaration":{"enter":[null]},"FunctionExpression":{"enter":[null]},"ObjectMethod":{"enter":[null]},"ArrowFunctionExpression":{"enter":[null]},"ClassMethod":{"enter":[null]},"ClassPrivateMethod":{"enter":[null]},"ForInStatement":{"enter":[null]},"ForOfStatement":{"enter":[null]}},"options":{}},{"key":"transform-literals","visitor":{"NumericLiteral":{"enter":[null]},"StringLiteral":{"enter":[null]},"_exploded":true,"_verified":true},"options":{}},{"key":"transform-template-literals","visitor":{"TaggedTemplateExpression":{"enter":[null]},"TemplateLiteral":{"enter":[null]},"_exploded":true,"_verified":true},"options":{}},{"key":"transform-parameters","visitor":{"_exploded":true,"_verified":true,"FunctionDeclaration":{"enter":[null]},"FunctionExpression":{"enter":[null]},"ObjectMethod":{"enter":[null]},"ArrowFunctionExpression":{"enter":[null]},"ClassMethod":{"enter":[null]},"ClassPrivateMethod":{"enter":[null]}},"options":{}},{"key":"transform-exponentiation-operator","visitor":{"AssignmentExpression":{"enter":[null]},"BinaryExpression":{"enter":[null]},"_exploded":true,"_verified":true},"options":{}}],"presets":[],"generatorOpts":{"filename":"/Users/tilenbabnik/Desktop/pgg/client/game/OutcomeStage.jsx","comments":true,"compact":false,"sourceMaps":true,"sourceFileName":"client/game/OutcomeStage.jsx"}},"code":"module.export({\n  default: () => OutcomeStage\n});\nlet React;\nmodule.link(\"react\", {\n  default(v) {\n    React = v;\n  }\n\n}, 0);\nlet ListView;\nmodule.link(\"./ListView.jsx\", {\n  default(v) {\n    ListView = v;\n  }\n\n}, 1);\nlet Collapsible;\nmodule.link(\"./Collapsible.jsx\", {\n  default(v) {\n    Collapsible = v;\n  }\n\n}, 2);\nlet PunishmentSocialDisplay;\nmodule.link(\"./PunishmentSocialDisplay.jsx\", {\n  default(v) {\n    PunishmentSocialDisplay = v;\n  }\n\n}, 3);\nlet Table;\nmodule.link(\"./Table.jsx\", {\n  default(v) {\n    Table = v;\n  }\n\n}, 4);\nmodule.link(\"./OutcomeStage.css\");\n\nclass OutcomeStage extends React.Component {\n  constructor(props) {\n    super(props);\n\n    this.onNext = event => {\n      event.preventDefault();\n      this.props.player.stage.submit();\n    };\n\n    this.state = {\n      summaryTab: true,\n      punishmentTab: false\n    };\n    history.toggleSummaryTab = this.toggleSummaryTab.bind(this);\n    history.togglePunishmentsTab = this.togglePunishmentsTab.bind(this);\n  }\n\n  toggleSummaryTab(e) {\n    this.setState({\n      summaryTab: true\n    });\n    this.setState({\n      punishmentsTab: false\n    });\n    document.getElementById(\"summaryTab\").className = \"tabs-button--true\";\n    document.getElementById(\"summaryContent\").className = \"tabs-content--true\";\n    document.getElementById(\"punishmentsTab\").className = \"tabs-button--false\";\n    document.getElementById(\"punishmentsContent\").className = \"tabs-content--false\";\n  }\n\n  togglePunishmentsTab(e) {\n    this.setState({\n      summaryTab: false\n    });\n    this.setState({\n      punishmentsTab: true\n    });\n    document.getElementById(\"summaryTab\").className = \"tabs-button--false\";\n    document.getElementById(\"summaryContent\").className = \"tabs-content--false\";\n    document.getElementById(\"punishmentsTab\").className = \"tabs-button--true\";\n    document.getElementById(\"punishmentsContent\").className = \"tabs-content--true\";\n  }\n\n  renderSubmitted() {\n    return /*#__PURE__*/React.createElement(\"div\", {\n      className: \"next-round center\"\n    }, /*#__PURE__*/React.createElement(\"div\", {\n      className: \"center\"\n    }, /*#__PURE__*/React.createElement(\"h5\", null, \"Waiting on other players...\"), \"Please wait until all players are ready\"));\n  }\n\n  render() {\n    /*const { hasNext, onNext, player, round } = this.props;*/\n    const {\n      game,\n      stage,\n      player,\n      round\n    } = this.props;\n    const payoff = round.get(\"payoff\");\n    const punished = player.round.get(\"punished\");\n    const costs = player.round.get(\"costs\");\n    const punishedBy = player.round.get(\"punishedBy\");\n    const penalties = player.round.get(\"penalties\");\n    const remainingEndowment = player.round.get(\"remainingEndowment\");\n    const roundPayoff = player.round.get(\"roundPayoff\");\n\n    const otherPlayers = _.reject(game.players, p => p._id === player._id);\n    /*\n    if (player.stage.submitted) {\n      return <body className=\"outcome-body\"> {this.renderSubmitted()} </body>;\n    }\n    */\n\n\n    return /*#__PURE__*/React.createElement(\"body\", {\n      className: \"outcome-body\"\n    }, /*#__PURE__*/React.createElement(\"div\", {\n      className: \"centered-text\"\n    }, /*#__PURE__*/React.createElement(\"div\", {\n      className: \"tabs-content--true\",\n      id: \"summaryContent\"\n    }, /*#__PURE__*/React.createElement(\"h4\", {\n      className: \"outcome-heading\"\n    }, \"Round Summary\"), /*#__PURE__*/React.createElement(Table, null), /*#__PURE__*/React.createElement(\"div\", null, /*#__PURE__*/React.createElement(\"div\", null, /*#__PURE__*/React.createElement(\"div\", {\n      className: \"outcome-subheading\"\n    }, /*#__PURE__*/React.createElement(\"div\", null, \" You punished \"), /*#__PURE__*/React.createElement(\"div\", null, \" Punished you \")), /*#__PURE__*/React.createElement(\"div\", {\n      className: \"punishment-display-container\"\n    }, /*#__PURE__*/React.createElement(\"div\", null, /*#__PURE__*/React.createElement(\"div\", {\n      className: \"left-div\"\n    }, /*#__PURE__*/React.createElement(\"h2\", null, /*#__PURE__*/React.createElement(ListView, {\n      punishments: punished,\n      game: game,\n      className: \"punishment-social-view\"\n    }))), /*#__PURE__*/React.createElement(\"span\", {\n      className: \"right-div\"\n    }, /*#__PURE__*/React.createElement(\"h2\", null, /*#__PURE__*/React.createElement(ListView, {\n      punishments: punishedBy,\n      game: game,\n      className: \"punishment-social-view\"\n    }))))), /*#__PURE__*/React.createElement(\"div\", {\n      className: \"summary\"\n    }, /*#__PURE__*/React.createElement(\"div\", {\n      className: \"payoff-container\"\n    }, /*#__PURE__*/React.createElement(\"div\", {\n      className: \"payoff-text\"\n    }, /*#__PURE__*/React.createElement(\"h2\", null, \" Round payoff: \", \" \"), /*#__PURE__*/React.createElement(\"h2\", null, \"Remaining endowment: \"), /*#__PURE__*/React.createElement(\"h2\", null, \" Punishment costs: \", \" \"), /*#__PURE__*/React.createElement(\"h2\", null, \"Punishment penalties: \"), /*#__PURE__*/React.createElement(\"div\", {\n      className: \"payoff-line\"\n    }), /*#__PURE__*/React.createElement(\"h1\", null, \"TOTAL\")), /*#__PURE__*/React.createElement(\"div\", {\n      className: \"payoff-numbers\"\n    }, /*#__PURE__*/React.createElement(\"h2\", null, \" \", payoff, \" MU \"), /*#__PURE__*/React.createElement(\"h2\", null, remainingEndowment, \" MU\"), /*#__PURE__*/React.createElement(\"h2\", {\n      className: \"outcome-costs\"\n    }, \" -\", costs, \" MU \"), /*#__PURE__*/React.createElement(\"h2\", {\n      className: \"outcome-costs\"\n    }, \" -\", penalties, \" MU\"), /*#__PURE__*/React.createElement(\"div\", {\n      className: \"payoff-line\"\n    }), roundPayoff >= 0 ? /*#__PURE__*/React.createElement(\"h1\", {\n      className: \"net-positive\"\n    }, \" + \", roundPayoff, \" MU \") : /*#__PURE__*/React.createElement(\"h1\", {\n      className: \"net-negative\"\n    }, \" \", roundPayoff, \" MU\"))))))), /*#__PURE__*/React.createElement(\"div\", {\n      className: \"tabs-content--false\",\n      id: \"punishmentsContent\"\n    }, /*#__PURE__*/React.createElement(\"h4\", {\n      className: \"outcome-heading\"\n    }, \"All Punishments\"), /*#__PURE__*/React.createElement(Collapsible, {\n      title: \"View All Punishments\",\n      children: otherPlayers.map(p => /*#__PURE__*/React.createElement(PunishmentSocialDisplay, {\n        game: game,\n        player: p,\n        me: player\n      })),\n      game: game,\n      player: player,\n      round: round\n    }))), /*#__PURE__*/React.createElement(\"div\", {\n      className: \"next-round center\"\n    }, player.stage.submitted ? /*#__PURE__*/React.createElement(\"body\", {\n      className: \"outcome-body\"\n    }, \" \", this.renderSubmitted(), \" \") : /*#__PURE__*/React.createElement(\"button\", {\n      type: \"button\",\n      onClick: this.onNext,\n      className: \"button\"\n    }, \"Next Round\")));\n  }\n\n}","map":{"version":3,"sources":["client/game/OutcomeStage.jsx"],"names":["module","export","default","OutcomeStage","React","link","v","ListView","Collapsible","PunishmentSocialDisplay","Table","Component","constructor","props","onNext","event","preventDefault","player","stage","submit","state","summaryTab","punishmentTab","history","toggleSummaryTab","bind","togglePunishmentsTab","e","setState","punishmentsTab","document","getElementById","className","renderSubmitted","render","game","round","payoff","get","punished","costs","punishedBy","penalties","remainingEndowment","roundPayoff","otherPlayers","_","reject","players","p","_id","map","submitted"],"mappings":"AAAAA,MAAM,CAACC,MAAP,CAAc;AAACC,EAAAA,OAAO,EAAC,MAAIC;AAAb,CAAd;AAA0C,IAAIC,KAAJ;AAAUJ,MAAM,CAACK,IAAP,CAAY,OAAZ,EAAoB;AAACH,EAAAA,OAAO,CAACI,CAAD,EAAG;AAACF,IAAAA,KAAK,GAACE,CAAN;AAAQ;;AAApB,CAApB,EAA0C,CAA1C;AAA6C,IAAIC,QAAJ;AAAaP,MAAM,CAACK,IAAP,CAAY,gBAAZ,EAA6B;AAACH,EAAAA,OAAO,CAACI,CAAD,EAAG;AAACC,IAAAA,QAAQ,GAACD,CAAT;AAAW;;AAAvB,CAA7B,EAAsD,CAAtD;AAAyD,IAAIE,WAAJ;AAAgBR,MAAM,CAACK,IAAP,CAAY,mBAAZ,EAAgC;AAACH,EAAAA,OAAO,CAACI,CAAD,EAAG;AAACE,IAAAA,WAAW,GAACF,CAAZ;AAAc;;AAA1B,CAAhC,EAA4D,CAA5D;AAA+D,IAAIG,uBAAJ;AAA4BT,MAAM,CAACK,IAAP,CAAY,+BAAZ,EAA4C;AAACH,EAAAA,OAAO,CAACI,CAAD,EAAG;AAACG,IAAAA,uBAAuB,GAACH,CAAxB;AAA0B;;AAAtC,CAA5C,EAAoF,CAApF;AAAuF,IAAII,KAAJ;AAAUV,MAAM,CAACK,IAAP,CAAY,aAAZ,EAA0B;AAACH,EAAAA,OAAO,CAACI,CAAD,EAAG;AAACI,IAAAA,KAAK,GAACJ,CAAN;AAAQ;;AAApB,CAA1B,EAAgD,CAAhD;AAAmDN,MAAM,CAACK,IAAP,CAAY,oBAAZ;;AAOvZ,MAAMF,YAAN,SAA2BC,KAAK,CAACO,SAAjC,CAA2C;AACxDC,EAAAA,WAAW,CAACC,KAAD,EAAQ;AACjB,UAAMA,KAAN;;AADiB,SAgCnBC,MAhCmB,GAgCTC,KAAD,IAAW;AAClBA,MAAAA,KAAK,CAACC,cAAN;AACA,WAAKH,KAAL,CAAWI,MAAX,CAAkBC,KAAlB,CAAwBC,MAAxB;AACD,KAnCkB;;AAGjB,SAAKC,KAAL,GAAa;AACXC,MAAAA,UAAU,EAAE,IADD;AAEXC,MAAAA,aAAa,EAAE;AAFJ,KAAb;AAIAC,IAAAA,OAAO,CAACC,gBAAR,GAA2B,KAAKA,gBAAL,CAAsBC,IAAtB,CAA2B,IAA3B,CAA3B;AACAF,IAAAA,OAAO,CAACG,oBAAR,GAA+B,KAAKA,oBAAL,CAA0BD,IAA1B,CAA+B,IAA/B,CAA/B;AACD;;AACDD,EAAAA,gBAAgB,CAACG,CAAD,EAAI;AAClB,SAAKC,QAAL,CAAc;AAAEP,MAAAA,UAAU,EAAE;AAAd,KAAd;AACA,SAAKO,QAAL,CAAc;AAAEC,MAAAA,cAAc,EAAE;AAAlB,KAAd;AAEAC,IAAAA,QAAQ,CAACC,cAAT,CAAwB,YAAxB,EAAsCC,SAAtC;AACAF,IAAAA,QAAQ,CAACC,cAAT,CAAwB,gBAAxB,EAA0CC,SAA1C;AACAF,IAAAA,QAAQ,CAACC,cAAT,CAAwB,gBAAxB,EAA0CC,SAA1C;AACAF,IAAAA,QAAQ,CAACC,cAAT,CACE,oBADF,EAEEC,SAFF;AAGD;;AACDN,EAAAA,oBAAoB,CAACC,CAAD,EAAI;AACtB,SAAKC,QAAL,CAAc;AAAEP,MAAAA,UAAU,EAAE;AAAd,KAAd;AACA,SAAKO,QAAL,CAAc;AAAEC,MAAAA,cAAc,EAAE;AAAlB,KAAd;AAEAC,IAAAA,QAAQ,CAACC,cAAT,CAAwB,YAAxB,EAAsCC,SAAtC;AACAF,IAAAA,QAAQ,CAACC,cAAT,CAAwB,gBAAxB,EAA0CC,SAA1C;AACAF,IAAAA,QAAQ,CAACC,cAAT,CAAwB,gBAAxB,EAA0CC,SAA1C;AACAF,IAAAA,QAAQ,CAACC,cAAT,CACE,oBADF,EAEEC,SAFF;AAGD;;AAMDC,EAAAA,eAAe,GAAG;AAChB,wBACE;AAAK,MAAA,SAAS,EAAC;AAAf,oBACE;AAAK,MAAA,SAAS,EAAC;AAAf,oBACE,8DADF,4CADF,CADF;AAQD;;AAEDC,EAAAA,MAAM,GAAG;AACP;AACA,UAAM;AAAEC,MAAAA,IAAF;AAAQjB,MAAAA,KAAR;AAAeD,MAAAA,MAAf;AAAuBmB,MAAAA;AAAvB,QAAiC,KAAKvB,KAA5C;AAEA,UAAMwB,MAAM,GAAGD,KAAK,CAACE,GAAN,CAAU,QAAV,CAAf;AACA,UAAMC,QAAQ,GAAGtB,MAAM,CAACmB,KAAP,CAAaE,GAAb,CAAiB,UAAjB,CAAjB;AACA,UAAME,KAAK,GAAGvB,MAAM,CAACmB,KAAP,CAAaE,GAAb,CAAiB,OAAjB,CAAd;AACA,UAAMG,UAAU,GAAGxB,MAAM,CAACmB,KAAP,CAAaE,GAAb,CAAiB,YAAjB,CAAnB;AACA,UAAMI,SAAS,GAAGzB,MAAM,CAACmB,KAAP,CAAaE,GAAb,CAAiB,WAAjB,CAAlB;AACA,UAAMK,kBAAkB,GAAG1B,MAAM,CAACmB,KAAP,CAAaE,GAAb,CAAiB,oBAAjB,CAA3B;AACA,UAAMM,WAAW,GAAG3B,MAAM,CAACmB,KAAP,CAAaE,GAAb,CAAiB,aAAjB,CAApB;;AACA,UAAMO,YAAY,GAAGC,CAAC,CAACC,MAAF,CAASZ,IAAI,CAACa,OAAd,EAAwBC,CAAD,IAAOA,CAAC,CAACC,GAAF,KAAUjC,MAAM,CAACiC,GAA/C,CAArB;AAEA;;;;;;;AAKA,wBACE;AAAM,MAAA,SAAS,EAAC;AAAhB,oBACE;AAAK,MAAA,SAAS,EAAC;AAAf,oBACE;AAAK,MAAA,SAAS,EAAC,oBAAf;AAAoC,MAAA,EAAE,EAAC;AAAvC,oBACE;AAAI,MAAA,SAAS,EAAC;AAAd,uBADF,eAEE,oBAAC,KAAD,OAFF,eAKE,8CACE,8CACE;AAAK,MAAA,SAAS,EAAC;AAAf,oBACE,kDADF,eAEE,kDAFF,CADF,eAKE;AAAK,MAAA,SAAS,EAAC;AAAf,oBACE,8CACE;AAAK,MAAA,SAAS,EAAC;AAAf,oBACE,6CAEE,oBAAC,QAAD;AACE,MAAA,WAAW,EAAEX,QADf;AAEE,MAAA,IAAI,EAAEJ,IAFR;AAGE,MAAA,SAAS,EAAC;AAHZ,MAFF,CADF,CADF,eAWE;AAAM,MAAA,SAAS,EAAC;AAAhB,oBACE,6CAGI,oBAAC,QAAD;AACE,MAAA,WAAW,EAAEM,UADf;AAEE,MAAA,IAAI,EAAEN,IAFR;AAGE,MAAA,SAAS,EAAC;AAHZ,MAHJ,CADF,CAXF,CADF,CALF,eA+BE;AAAK,MAAA,SAAS,EAAC;AAAf,oBACE;AAAK,MAAA,SAAS,EAAC;AAAf,oBACE;AAAK,MAAA,SAAS,EAAC;AAAf,oBACE,uDADF,eAEE,wDAFF,eAKE,2DALF,eAME,yDANF,eAOE;AAAK,MAAA,SAAS,EAAC;AAAf,MAPF,eASE,wCATF,CADF,eAYE;AAAK,MAAA,SAAS,EAAC;AAAf,oBACE,qCAAME,MAAN,SADF,eAEE,gCAAKM,kBAAL,QAFF,eAGE;AAAI,MAAA,SAAS,EAAC;AAAd,aAAiCH,KAAjC,SAHF,eAIE;AAAI,MAAA,SAAS,EAAC;AAAd,aAAiCE,SAAjC,QAJF,eAKE;AAAK,MAAA,SAAS,EAAC;AAAf,MALF,EAMGE,WAAW,IAAI,CAAf,gBACC;AAAI,MAAA,SAAS,EAAC;AAAd,cAAiCA,WAAjC,SADD,gBAGC;AAAI,MAAA,SAAS,EAAC;AAAd,YAA+BA,WAA/B,QATJ,CAZF,CADF,CA/BF,CADF,CALF,CADF,eAoEE;AAAK,MAAA,SAAS,EAAC,qBAAf;AAAqC,MAAA,EAAE,EAAC;AAAxC,oBACE;AAAI,MAAA,SAAS,EAAC;AAAd,yBADF,eAEE,oBAAC,WAAD;AACE,MAAA,KAAK,EAAE,sBADT;AAEE,MAAA,QAAQ,EAAEC,YAAY,CAACM,GAAb,CAAkBF,CAAD,iBACzB,oBAAC,uBAAD;AAAyB,QAAA,IAAI,EAAEd,IAA/B;AAAqC,QAAA,MAAM,EAAEc,CAA7C;AAAgD,QAAA,EAAE,EAAEhC;AAApD,QADQ,CAFZ;AAKE,MAAA,IAAI,EAAEkB,IALR;AAME,MAAA,MAAM,EAAElB,MANV;AAOE,MAAA,KAAK,EAAEmB;AAPT,MAFF,CApEF,CADF,eAkFE;AAAK,MAAA,SAAS,EAAC;AAAf,OACGnB,MAAM,CAACC,KAAP,CAAakC,SAAb,gBACC;AAAM,MAAA,SAAS,EAAC;AAAhB,YAAiC,KAAKnB,eAAL,EAAjC,MADD,gBAGC;AAAQ,MAAA,IAAI,EAAC,QAAb;AAAsB,MAAA,OAAO,EAAE,KAAKnB,MAApC;AAA4C,MAAA,SAAS,EAAC;AAAtD,oBAJJ,CAlFF,CADF;AA8FD;;AAjKuD","sourcesContent":["import React from \"react\";\nimport ListView from \"./ListView.jsx\";\nimport Collapsible from \"./Collapsible.jsx\";\nimport PunishmentSocialDisplay from \"./PunishmentSocialDisplay.jsx\";\nimport Table from \"./Table.jsx\";\nimport \"./OutcomeStage.css\";\n\nexport default class OutcomeStage extends React.Component {\n  constructor(props) {\n    super(props);\n\n    this.state = {\n      summaryTab: true,\n      punishmentTab: false,\n    };\n    history.toggleSummaryTab = this.toggleSummaryTab.bind(this);\n    history.togglePunishmentsTab = this.togglePunishmentsTab.bind(this);\n  }\n  toggleSummaryTab(e) {\n    this.setState({ summaryTab: true });\n    this.setState({ punishmentsTab: false });\n\n    document.getElementById(\"summaryTab\").className = `tabs-button--true`;\n    document.getElementById(\"summaryContent\").className = `tabs-content--true`;\n    document.getElementById(\"punishmentsTab\").className = `tabs-button--false`;\n    document.getElementById(\n      \"punishmentsContent\"\n    ).className = `tabs-content--false`;\n  }\n  togglePunishmentsTab(e) {\n    this.setState({ summaryTab: false });\n    this.setState({ punishmentsTab: true });\n\n    document.getElementById(\"summaryTab\").className = `tabs-button--false`;\n    document.getElementById(\"summaryContent\").className = `tabs-content--false`;\n    document.getElementById(\"punishmentsTab\").className = `tabs-button--true`;\n    document.getElementById(\n      \"punishmentsContent\"\n    ).className = `tabs-content--true`;\n  }\n  onNext = (event) => {\n    event.preventDefault();\n    this.props.player.stage.submit();\n  };\n\n  renderSubmitted() {\n    return (\n      <div className=\"next-round center\">\n        <div className=\"center\">\n          <h5>Waiting on other players...</h5>\n          Please wait until all players are ready\n        </div>\n      </div>\n    );\n  }\n\n  render() {\n    /*const { hasNext, onNext, player, round } = this.props;*/\n    const { game, stage, player, round } = this.props;\n\n    const payoff = round.get(\"payoff\");\n    const punished = player.round.get(\"punished\");\n    const costs = player.round.get(\"costs\");\n    const punishedBy = player.round.get(\"punishedBy\");\n    const penalties = player.round.get(\"penalties\");\n    const remainingEndowment = player.round.get(\"remainingEndowment\");\n    const roundPayoff = player.round.get(\"roundPayoff\");\n    const otherPlayers = _.reject(game.players, (p) => p._id === player._id);\n\n    /*\n    if (player.stage.submitted) {\n      return <body className=\"outcome-body\"> {this.renderSubmitted()} </body>;\n    }\n*/\n    return (\n      <body className=\"outcome-body\">\n        <div className=\"centered-text\">\n          <div className=\"tabs-content--true\" id=\"summaryContent\">\n            <h4 className=\"outcome-heading\">Round Summary</h4>\n            <Table \n            \n            />\n            <div>\n              <div>\n                <div className=\"outcome-subheading\">\n                  <div> You punished </div>\n                  <div> Punished you </div>\n                </div>\n                <div className=\"punishment-display-container\">\n                  <div>\n                    <div className=\"left-div\">\n                      <h2>\n                        {/*You punished:*/}\n                        <ListView\n                          punishments={punished}\n                          game={game}\n                          className=\"punishment-social-view\"\n                        />\n                      </h2>\n                    </div>\n                    <span className=\"right-div\">\n                      <h2>\n                        {/*Punished you:{\" \"}*/}\n                        {\n                          <ListView\n                            punishments={punishedBy}\n                            game={game}\n                            className=\"punishment-social-view\"\n                          />\n                        }\n                      </h2>\n                    </span>\n                  </div>\n                </div>\n                <div className=\"summary\">\n                  <div className=\"payoff-container\">\n                    <div className=\"payoff-text\">\n                      <h2> Round payoff: {/*{payoff} MU*/} </h2>\n                      <h2>\n                        Remaining endowment: {/*{remainingEndowment} MU*/}\n                      </h2>\n                      <h2> Punishment costs: {/*} -{costs} MU */} </h2>\n                      <h2>Punishment penalties: {/*-{penalties} MU*/}</h2>\n                      <div className=\"payoff-line\"></div>\n\n                      <h1>TOTAL</h1>\n                    </div>\n                    <div className=\"payoff-numbers\">\n                      <h2> {payoff} MU </h2>\n                      <h2>{remainingEndowment} MU</h2>\n                      <h2 className=\"outcome-costs\"> -{costs} MU </h2>\n                      <h2 className=\"outcome-costs\"> -{penalties} MU</h2>\n                      <div className=\"payoff-line\"></div>\n                      {roundPayoff >= 0 ? (\n                        <h1 className=\"net-positive\"> + {roundPayoff} MU </h1>\n                      ) : (\n                        <h1 className=\"net-negative\"> {roundPayoff} MU</h1>\n                      )}\n                    </div>\n                  </div>\n                </div>\n              </div>\n            </div>\n          </div>\n          <div className=\"tabs-content--false\" id=\"punishmentsContent\">\n            <h4 className=\"outcome-heading\">All Punishments</h4>\n            <Collapsible\n              title={\"View All Punishments\"}\n              children={otherPlayers.map((p) => (\n                <PunishmentSocialDisplay game={game} player={p} me={player} />\n              ))}\n              game={game}\n              player={player}\n              round={round}\n            ></Collapsible>\n          </div>\n        </div>\n        <div className=\"next-round center\">\n          {player.stage.submitted ? (\n            <body className=\"outcome-body\"> {this.renderSubmitted()} </body>\n          ) : (\n            <button type=\"button\" onClick={this.onNext} className=\"button\">\n              Next Round\n            </button>\n          )}\n        </div>\n      </body>\n    );\n  }\n}\n"]},"sourceType":"module","hash":"b7d4d771976f84ce2cdf01571500940d6867dae1"}
